equivariance_regularizer/__init__.py
equivariance_regularizer/equivariance_regularizer.py
equivariance_regularizer-0.1.1.dist-info/METADATA
equivariance_regularizer-0.1.1.dist-info/WHEEL
equivariance_regularizer-0.1.1.dist-info/licenses/LICENSE
equivariance_regularizer-0.1.1.dist-info/RECORD
