Metadata-Version: 2.3
Name: equivariance_regularizer
Version: 0.1.1
Summary: An equivariance regularization term for PyTorch.
Project-URL: Homepage, https://github.com/jjkjjk23/Equivariance-Regularizer
Author: Jacob Keller
License-File: LICENSE
Classifier: License :: OSI Approved :: MIT License
Classifier: Operating System :: OS Independent
Classifier: Programming Language :: Python :: 3
Requires-Python: >=3.7
